full_adder.v
`timescale 10ns/1ns

module full_adder(s,cout,a,b,c);
    output s,cout;
    input a,b,c;
    wire t1,t2,t3;
    xor x1(s,a,b,c);
    and a1(t1,a,b);
    and a2(t2,b,c);
    and a3(t3,a,c);
    or o1(cout,t1,t2,t3);

endmodule

full_adder_tb.v
`timescale 10ns/1ns
`include "full_adder.v"

module full_adder_tb;
    reg a,b,c;
    wire s,cout;
    full_adder DUT(.a(a),.b(b),.c(c),.s(s),.cout(cout));
    initial begin
        $dumpfile("fulladder.vcd");
        $dumpvars(0,full_adder_tb);
        $monitor($time,"A=%b,B=%b,C=%b,S=%b,COUT=%b",a,b,c,s,cout);
        #5 a=0;b=0;c=0;
        #5 a=0;b=0;c=1;
        #5 a=0;b=1;c=0;
        #5 a=0;b=1;c=1;
        #5 a=1;b=0;c=0;
        #5 a=1;b=0;c=1;
        #5 a=1;b=1;c=0;
        #5 a=1;b=1;c=1;
        #5
        $finish;
    end
endmodule

fulladder.vcd
$date
	Tue Jun 17 22:33:58 2025
$end
$version
	Icarus Verilog
$end
$timescale
	1ns
$end
$scope module full_adder_tb $end
$var wire 1 ! s $end
$var wire 1 " cout $end
$var reg 1 # a $end
$var reg 1 $ b $end
$var reg 1 % c $end
$scope module DUT $end
$var wire 1 # a $end
$var wire 1 $ b $end
$var wire 1 % c $end
$var wire 1 " cout $end
$var wire 1 ! s $end
$var wire 1 & t1 $end
$var wire 1 ' t2 $end
$var wire 1 ( t3 $end
$upscope $end
$upscope $end
$enddefinitions $end
$comment Show the parameter values. $end
$dumpall
$end
#0
$dumpvars
x(
x'
x&
x%
x$
x#
x"
x!
$end
#50
0"
0'
0!
0&
0(
0%
0$
0#
#100
1!
1%
#150
0%
1$
#200
1"
0!
1'
1%
#250
0"
0'
1!
0%
0$
1#
#300
1"
0!
1(
1%
#350
0(
1&
0%
1$
#400
1!
1'
1(
1%
